pycombinators.py
pycombinators-1.0.2.dist-info/LICENSE
pycombinators-1.0.2.dist-info/METADATA
pycombinators-1.0.2.dist-info/WHEEL
pycombinators-1.0.2.dist-info/top_level.txt
pycombinators-1.0.2.dist-info/RECORD
