Metadata-Version: 2.1
Name: pycombinators
Version: 1.0.2
Summary: Elementary combinators in Python inspired by LISP and Haskell. Mostly a convenience library for my sake.
Home-page: https://github.com/Evan-Hock/pycombinators
Author: Evan Hock
Author-email: mocaointegral@gmail.com
Classifier: Programming Language :: Python :: 3.10
Classifier: License :: OSI Approved :: GNU General Public License v3 (GPLv3)
Classifier: Operating System :: OS Independent
Requires-Python: >=3.10
License-File: LICENSE
